nti/__init__.py
nti/site/__init__.py
nti/site/configure.zcml
nti/site/folder.py
nti/site/hostpolicy.py
nti/site/interfaces.py
nti/site/localutility.py
nti/site/meta.zcml
nti/site/runner.py
nti/site/site.py
nti/site/subscribers.py
nti/site/testing.py
nti/site/transient.py
nti/site/utils.py
nti/site/zcml.py
nti/site/tests/__init__.py
nti/site/tests/test_localutility.py
nti/site/tests/test_runner.py
nti/site/tests/test_site.py
nti/site/tests/test_subscribers.py
nti/site/tests/test_sync.py
nti/site/tests/test_testing.py
nti/site/tests/test_transient.py
nti/site/tests/test_utils.py
nti/site/tests/test_zcml.py
nti.site-3.1.0.dist-info/AUTHORS
nti.site-3.1.0.dist-info/LICENSE
nti.site-3.1.0.dist-info/METADATA
nti.site-3.1.0.dist-info/WHEEL
nti.site-3.1.0.dist-info/top_level.txt
nti.site-3.1.0.dist-info/zip-safe
nti.site-3.1.0.dist-info/RECORD
