Metadata-Version: 2.1
Name: nti.site
Version: 3.1.0
Summary: Opinionated ZODB persistent site implementations
Home-page: https://github.com/OpenNTI/nti.site
Author: Jason Madden
Author-email: jason@nextthought.com
License: Apache
Keywords: Site management
Classifier: Intended Audience :: Developers
Classifier: Natural Language :: English
Classifier: Operating System :: OS Independent
Classifier: Development Status :: 5 - Production/Stable
Classifier: License :: OSI Approved :: Apache Software License
Classifier: Programming Language :: Python :: 3 :: Only
Classifier: Programming Language :: Python :: 3
Classifier: Programming Language :: Python :: 3.10
Classifier: Programming Language :: Python :: 3.11
Classifier: Programming Language :: Python :: 3.12
Classifier: Programming Language :: Python :: 3.13
Classifier: Programming Language :: Python :: Implementation :: CPython
Classifier: Programming Language :: Python :: Implementation :: PyPy
Requires-Python: >=3.10
License-File: LICENSE
License-File: AUTHORS
Requires-Dist: BTrees>=4.3.2
Requires-Dist: ZODB>=5.6.0
Requires-Dist: nti.schema
Requires-Dist: nti.transactions>=4.0.0
Requires-Dist: persistent
Requires-Dist: six
Requires-Dist: transaction>=2.4.0
Requires-Dist: zope.component>=5.0.0
Requires-Dist: zope.container
Requires-Dist: zope.interface>=5.3.0a1
Requires-Dist: zope.location
Requires-Dist: zope.proxy
Requires-Dist: zope.site>=4.4.0
Requires-Dist: zope.traversing
Provides-Extra: docs
Requires-Dist: Sphinx; extra == "docs"
Requires-Dist: repoze.sphinx.autointerface; extra == "docs"
Requires-Dist: sphinx-rtd-theme; extra == "docs"
Requires-Dist: nti.testing>=3.0.0; extra == "docs"
Requires-Dist: pyhamcrest; extra == "docs"
Requires-Dist: z3c.baseregistry; extra == "docs"
Requires-Dist: zope.testrunner; extra == "docs"
Requires-Dist: coverage; extra == "docs"
Requires-Dist: zope.testing; extra == "docs"
Provides-Extra: test
Requires-Dist: nti.testing>=3.0.0; extra == "test"
Requires-Dist: pyhamcrest; extra == "test"
Requires-Dist: z3c.baseregistry; extra == "test"
Requires-Dist: zope.testrunner; extra == "test"
Requires-Dist: coverage; extra == "test"
Requires-Dist: zope.testing; extra == "test"
